README.md
setup.py
restrictedboosting/__init__.py
restrictedboosting/restrictedboostclassifier.py
restrictedensemble.egg-info/PKG-INFO
restrictedensemble.egg-info/SOURCES.txt
restrictedensemble.egg-info/dependency_links.txt
restrictedensemble.egg-info/requires.txt
restrictedensemble.egg-info/top_level.txt